[{"id":"2003-MO-029","title":"Wise v. State","url":"http://www.judicial.state.sc.us/opinions/displayUnPubOpinion.cfm?caseNo=2003-MO-029","description":null,"date":"2003-04-07","type":"opinion","text":null,"court":"Supreme"},{"id":"2003-MO-030","title":"Fiskling v. Taylor & Murphy Construction","url":"http://www.judicial.state.sc.us/opinions/displayUnPubOpinion.cfm?caseNo=2003-MO-030","description":null,"date":"2003-04-07","type":"opinion","text":null,"court":"Supreme"},{"id":"2003-MO-031","title":"Clark v. Greenville County","url":"http://www.judicial.state.sc.us/opinions/displayUnPubOpinion.cfm?caseNo=2003-MO-031","description":null,"date":"2003-04-28","type":"opinion","text":null,"court":"Supreme"},{"id":"2003-MO-032","title":"Munn v. State","url":"http://www.judicial.state.sc.us/opinions/displayUnPubOpinion.cfm?caseNo=2003-MO-032","description":null,"date":"2003-04-28","type":"opinion","text":null,"court":"Supreme"}]